{"cameraMode":{"drawMode":0,"name":"Shaded","section":"Shading Mode"},"sceneLighting":true,"audioPlay":false,"sceneViewState":{"m_AlwaysRefresh":false,"showFog":true,"showSkybox":true,"showFlares":true,"showImageEffects":true,"showParticleSystems":true,"showVisualEffectGraphs":true,"m_FxEnabled":true},"in2DMode":false,"pivot":{"x":0.2920115888118744,"y":5.0,"z":-10.01574420928955},"rotation":{"x":0.047486260533332828,"y":0.7167966961860657,"z":-0.04905083775520325,"w":0.6939355134963989},"size":10.0,"orthographic":true}